[
  {
    "球種": "ストレート",
    "球数": 550,
    "割合": "67.5%",
    "平均球速 (km/h)": "150.1",
    "空振り": 100,
    "見逃し": 70,
    "ファウル": 137,
    "ボール": 160,
    "ストライク 割合": "55.8%",
    "Whiff%": "31.3%",
    "被打率": ".177",
    "被打数": 130,
    "被安": 23,
    "被本": 2,
    "奪三振": 50,
    "与四球": 6,
    "与死球": 0
  },
  {
    "球種": "フォーク",
    "球数": 171,
    "割合": "21.0%",
    "平均球速 (km/h)": "137.8",
    "空振り": 31,
    "見逃し": 21,
    "ファウル": 32,
    "ボール": 70,
    "ストライク 割合": "49.1%",
    "Whiff%": "38.8%",
    "被打率": ".059",
    "被打数": 34,
    "被安": 2,
    "被本": 0,
    "奪三振": 17,
    "与四球": 4,
    "与死球": 0
  },
  {
    "球種": "チェンジアップ",
    "球数": 47,
    "割合": "5.8%",
    "平均球速 (km/h)": "127.3",
    "空振り": 10,
    "見逃し": 10,
    "ファウル": 7,
    "ボール": 16,
    "ストライク 割合": "57.4%",
    "Whiff%": "47.6%",
    "被打率": ".200",
    "被打数": 5,
    "被安": 1,
    "被本": 1,
    "奪三振": 1,
    "与四球": 0,
    "与死球": 0
  },
  {
    "球種": "カットボール",
    "球数": 36,
    "割合": "4.4%",
    "平均球速 (km/h)": "140.1",
    "空振り": 3,
    "見逃し": 5,
    "ファウル": 7,
    "ボール": 17,
    "ストライク 割合": "41.7%",
    "Whiff%": "21.4%",
    "被打率": ".600",
    "被打数": 5,
    "被安": 3,
    "被本": 0,
    "奪三振": 1,
    "与四球": 2,
    "与死球": 0
  },
  {
    "球種": "ナックルカーブ",
    "球数": 9,
    "割合": "1.1%",
    "平均球速 (km/h)": "116.2",
    "空振り": 0,
    "見逃し": 2,
    "ファウル": 0,
    "ボール": 6,
    "ストライク 割合": "22.2%",
    "Whiff%": "0.0%",
    "被打率": ".000",
    "被打数": 2,
    "被安": 0,
    "被本": 0,
    "奪三振": 1,
    "与四球": 0,
    "与死球": 0
  },
  {
    "球種": "スライダー",
    "球数": 1,
    "割合": "0.1%",
    "平均球速 (km/h)": "125.0",
    "空振り": 0,
    "見逃し": 0,
    "ファウル": 0,
    "ボール": 1,
    "ストライク 割合": "0.0%",
    "Whiff%": "-%",
    "被打率": "-",
    "被打数": 0,
    "被安": 0,
    "被本": 0,
    "奪三振": 0,
    "与四球": 0,
    "与死球": 0
  },
  {
    "球種": "シンカー",
    "球数": 1,
    "割合": "0.1%",
    "平均球速 (km/h)": "-",
    "空振り": 0,
    "見逃し": 0,
    "ファウル": 1,
    "ボール": 0,
    "ストライク 割合": "100.0%",
    "Whiff%": "0.0%",
    "被打率": "-",
    "被打数": 0,
    "被安": 0,
    "被本": 0,
    "奪三振": 0,
    "与四球": 0,
    "与死球": 0
  }
]