[
  {
    "NOI386.0": "BB/K",
    "GPA.189": "IsoD",
    "RC1.15": "PA/BB",
    "RC271.82": "PA/K",
    "XR1.24": "IsoP",
    "XR271.96": "AB/HR",
    "RCAA-1.13": "SecA",
    "XR+-1.06": "TA",
    "RCWIN-0.13": "PS",
    "XRWIN-0.12": "TTO率",
    "BABIP.273": NaN
  },
  {
    "NOI386.0": "0.63",
    "GPA.189": "0.175",
    "RC1.15": "4.80",
    "RC271.82": "3.00",
    "XR1.24": "-0.000",
    "XR271.96": "-",
    "RCAA-1.13": "0.263",
    "XR+-1.06": "0.471",
    "RCWIN-0.13": "-",
    "XRWIN-0.12": "54.2%",
    "BABIP.273": NaN
  }
]