[
  {
    "NOI611.1": "BB/K",
    "GPA.308": "IsoD",
    "RC0.70": "PA/BB",
    "RC276.34": "PA/K",
    "XR0.68": "IsoP",
    "XR276.16": "AB/HR",
    "RCAA0.21": "SecA",
    "XR+0.19": "TA",
    "RCWIN0.02": "PS",
    "XRWIN0.02": "TTO率",
    "BABIP1.000": NaN
  },
  {
    "NOI611.1": "0.50",
    "GPA.308": "0.167",
    "RC0.70": "5.00",
    "RC276.34": "2.50",
    "XR0.68": "0.000",
    "XR276.16": "-",
    "RCAA0.21": "0.333",
    "XR+0.19": "1.000",
    "RCWIN0.02": "-",
    "XRWIN0.02": "60.0%",
    "BABIP1.000": NaN
  }
]