[
  {
    "球種": "ストレート",
    "球数": 1016,
    "割合": "45.6%",
    "平均球速 (km/h)": "146.6",
    "空振り": 43,
    "見逃し": 240,
    "ファウル": 187,
    "ボール": 350,
    "ストライク 割合": "46.3%",
    "Whiff%": "10.1%",
    "打率": ".307",
    "打数": 215,
    "安打": 66,
    "ＨＲ": 2,
    "三振": 25,
    "四球": 27,
    "死球": 1
  },
  {
    "球種": "スライダー",
    "球数": 311,
    "割合": "14.0%",
    "平均球速 (km/h)": "128.5",
    "空振り": 17,
    "見逃し": 66,
    "ファウル": 44,
    "ボール": 122,
    "ストライク 割合": "40.8%",
    "Whiff%": "13.8%",
    "打率": ".205",
    "打数": 73,
    "安打": 15,
    "ＨＲ": 0,
    "三振": 11,
    "四球": 7,
    "死球": 0
  },
  {
    "球種": "カットボール",
    "球数": 264,
    "割合": "11.8%",
    "平均球速 (km/h)": "137.0",
    "空振り": 15,
    "見逃し": 50,
    "ファウル": 53,
    "ボール": 89,
    "ストライク 割合": "44.7%",
    "Whiff%": "12.0%",
    "打率": ".339",
    "打数": 62,
    "安打": 21,
    "ＨＲ": 3,
    "三振": 8,
    "四球": 4,
    "死球": 1
  },
  {
    "球種": "フォーク",
    "球数": 158,
    "割合": "7.1%",
    "平均球速 (km/h)": "135.8",
    "空振り": 11,
    "見逃し": 23,
    "ファウル": 26,
    "ボール": 63,
    "ストライク 割合": "38.0%",
    "Whiff%": "15.3%",
    "打率": ".385",
    "打数": 39,
    "安打": 15,
    "ＨＲ": 1,
    "三振": 5,
    "四球": 2,
    "死球": 0
  },
  {
    "球種": "チェンジアップ",
    "球数": 155,
    "割合": "7.0%",
    "平均球速 (km/h)": "131.8",
    "空振り": 7,
    "見逃し": 18,
    "ファウル": 23,
    "ボール": 66,
    "ストライク 割合": "31.0%",
    "Whiff%": "9.9%",
    "打率": ".205",
    "打数": 44,
    "安打": 9,
    "ＨＲ": 0,
    "三振": 3,
    "四球": 2,
    "死球": 0
  },
  {
    "球種": "カーブ",
    "球数": 99,
    "割合": "4.4%",
    "平均球速 (km/h)": "117.0",
    "空振り": 4,
    "見逃し": 9,
    "ファウル": 18,
    "ボール": 47,
    "ストライク 割合": "31.3%",
    "Whiff%": "9.3%",
    "打率": ".500",
    "打数": 24,
    "安打": 12,
    "ＨＲ": 0,
    "三振": 3,
    "四球": 0,
    "死球": 1
  },
  {
    "球種": "ツーシーム",
    "球数": 94,
    "割合": "4.2%",
    "平均球速 (km/h)": "141.2",
    "空振り": 7,
    "見逃し": 15,
    "ファウル": 18,
    "ボール": 35,
    "ストライク 割合": "42.6%",
    "Whiff%": "15.9%",
    "打率": ".143",
    "打数": 21,
    "安打": 3,
    "ＨＲ": 0,
    "三振": 2,
    "四球": 2,
    "死球": 1
  },
  {
    "球種": "スプリット",
    "球数": 47,
    "割合": "2.1%",
    "平均球速 (km/h)": "139.3",
    "空振り": 3,
    "見逃し": 6,
    "ファウル": 10,
    "ボール": 19,
    "ストライク 割合": "40.4%",
    "Whiff%": "13.6%",
    "打率": ".400",
    "打数": 10,
    "安打": 4,
    "ＨＲ": 0,
    "三振": 1,
    "四球": 1,
    "死球": 0
  },
  {
    "球種": "シュート",
    "球数": 36,
    "割合": "1.6%",
    "平均球速 (km/h)": "141.3",
    "空振り": 1,
    "見逃し": 5,
    "ファウル": 5,
    "ボール": 17,
    "ストライク 割合": "30.6%",
    "Whiff%": "7.1%",
    "打率": ".222",
    "打数": 9,
    "安打": 2,
    "ＨＲ": 0,
    "三振": 1,
    "四球": 0,
    "死球": 0
  },
  {
    "球種": "シンカー",
    "球数": 19,
    "割合": "0.9%",
    "平均球速 (km/h)": "130.8",
    "空振り": 1,
    "見逃し": 1,
    "ファウル": 2,
    "ボール": 7,
    "ストライク 割合": "21.1%",
    "Whiff%": "9.1%",
    "打率": ".500",
    "打数": 8,
    "安打": 4,
    "ＨＲ": 0,
    "三振": 0,
    "四球": 0,
    "死球": 0
  },
  {
    "球種": "ナックルカーブ",
    "球数": 18,
    "割合": "0.8%",
    "平均球速 (km/h)": "127.5",
    "空振り": 1,
    "見逃し": 4,
    "ファウル": 3,
    "ボール": 6,
    "ストライク 割合": "44.4%",
    "Whiff%": "12.5%",
    "打率": ".400",
    "打数": 5,
    "安打": 2,
    "ＨＲ": 0,
    "三振": 1,
    "四球": 0,
    "死球": 0
  },
  {
    "球種": "縦スライダー",
    "球数": 5,
    "割合": "0.2%",
    "平均球速 (km/h)": "124.4",
    "空振り": 1,
    "見逃し": 3,
    "ファウル": 0,
    "ボール": 1,
    "ストライク 割合": "80.0%",
    "Whiff%": "100.0%",
    "打率": "-",
    "打数": 0,
    "安打": 0,
    "ＨＲ": 0,
    "三振": 0,
    "四球": 0,
    "死球": 0
  },
  {
    "球種": "パワーカーブ",
    "球数": 3,
    "割合": "0.1%",
    "平均球速 (km/h)": "122.3",
    "空振り": 0,
    "見逃し": 2,
    "ファウル": 0,
    "ボール": 0,
    "ストライク 割合": "66.7%",
    "Whiff%": "0.0%",
    "打率": ".000",
    "打数": 1,
    "安打": 0,
    "ＨＲ": 0,
    "三振": 0,
    "四球": 0,
    "死球": 0
  },
  {
    "球種": "スラーブ",
    "球数": 1,
    "割合": "0.0%",
    "平均球速 (km/h)": "101.0",
    "空振り": 0,
    "見逃し": 0,
    "ファウル": 0,
    "ボール": 1,
    "ストライク 割合": "0.0%",
    "Whiff%": "-%",
    "打率": "-",
    "打数": 0,
    "安打": 0,
    "ＨＲ": 0,
    "三振": 0,
    "四球": 0,
    "死球": 0
  },
  {
    "球種": "パーム",
    "球数": 1,
    "割合": "0.0%",
    "平均球速 (km/h)": "113.0",
    "空振り": 0,
    "見逃し": 0,
    "ファウル": 0,
    "ボール": 0,
    "ストライク 割合": "0.0%",
    "Whiff%": "0.0%",
    "打率": "1.000",
    "打数": 1,
    "安打": 1,
    "ＨＲ": 0,
    "三振": 0,
    "四球": 0,
    "死球": 0
  },
  {
    "球種": "ワンシーム",
    "球数": 1,
    "割合": "0.0%",
    "平均球速 (km/h)": "-",
    "空振り": 0,
    "見逃し": 0,
    "ファウル": 0,
    "ボール": 1,
    "ストライク 割合": "0.0%",
    "Whiff%": "-%",
    "打率": "-",
    "打数": 0,
    "安打": 0,
    "ＨＲ": 0,
    "三振": 0,
    "四球": 0,
    "死球": 0
  }
]