[
  {
    "NOI195.0": "BB/K",
    "GPA.107": "IsoD",
    "RC-0.45": "PA/BB",
    "RC27-0.25": "PA/K",
    "XR-0.31": "IsoP",
    "XR27-0.17": "AB/HR",
    "RCAA-5.78": "SecA",
    "XR+-5.66": "TA",
    "RCWIN-0.68": "PS",
    "XRWIN-0.67": "TTO率",
    "BABIP.163": NaN
  },
  {
    "NOI195.0": "0.00",
    "GPA.107": "0.000",
    "RC-0.45": "-",
    "RC27-0.25": "5.60",
    "XR-0.31": "0.057",
    "XR27-0.17": "-",
    "RCAA-5.78": "0.057",
    "XR+-5.66": "0.213",
    "RCWIN-0.68": "-",
    "XRWIN-0.67": "17.9%",
    "BABIP.163": NaN
  }
]