[
  {
    "月名": "3・4月",
    "打率": "-",
    "試合": 0,
    "打席": 0,
    "打数": 0,
    "得点": 0,
    "安打": 0,
    "２Ｂ": 0,
    "３Ｂ": 0,
    "本塁": 0,
    "塁打": 0,
    "打点": 0,
    "三振": 0,
    "四球": 0,
    "敬遠": 0,
    "死球": 0,
    "犠打": 0,
    "犠飛": 0,
    "盗塁": 0,
    "盗塁死": 0,
    "失策": 0,
    "出塁率": "-",
    "長打率": "-",
    "OPS": 0.0
  },
  {
    "月名": "5月",
    "打率": ".279",
    "試合": 21,
    "打席": 95,
    "打数": 86,
    "得点": 9,
    "安打": 24,
    "２Ｂ": 3,
    "３Ｂ": 0,
    "本塁": 0,
    "塁打": 27,
    "打点": 3,
    "三振": 11,
    "四球": 5,
    "敬遠": 0,
    "死球": 1,
    "犠打": 3,
    "犠飛": 0,
    "盗塁": 4,
    "盗塁死": 0,
    "失策": 0,
    "出塁率": ".326",
    "長打率": ".314",
    "OPS": 0.64
  },
  {
    "月名": "6月",
    "打率": ".172",
    "試合": 19,
    "打席": 73,
    "打数": 64,
    "得点": 6,
    "安打": 11,
    "２Ｂ": 3,
    "３Ｂ": 2,
    "本塁": 0,
    "塁打": 18,
    "打点": 3,
    "三振": 13,
    "四球": 6,
    "敬遠": 1,
    "死球": 3,
    "犠打": 0,
    "犠飛": 0,
    "盗塁": 2,
    "盗塁死": 0,
    "失策": 0,
    "出塁率": ".274",
    "長打率": ".281",
    "OPS": 0.555
  },
  {
    "月名": "7月",
    "打率": ".304",
    "試合": 21,
    "打席": 88,
    "打数": 79,
    "得点": 8,
    "安打": 24,
    "２Ｂ": 1,
    "３Ｂ": 0,
    "本塁": 1,
    "塁打": 28,
    "打点": 2,
    "三振": 13,
    "四球": 7,
    "敬遠": 0,
    "死球": 1,
    "犠打": 1,
    "犠飛": 0,
    "盗塁": 1,
    "盗塁死": 0,
    "失策": 0,
    "出塁率": ".368",
    "長打率": ".354",
    "OPS": 0.722
  },
  {
    "月名": "8月",
    "打率": ".293",
    "試合": 22,
    "打席": 90,
    "打数": 82,
    "得点": 9,
    "安打": 24,
    "２Ｂ": 5,
    "３Ｂ": 0,
    "本塁": 2,
    "塁打": 35,
    "打点": 6,
    "三振": 8,
    "四球": 6,
    "敬遠": 0,
    "死球": 1,
    "犠打": 1,
    "犠飛": 0,
    "盗塁": 2,
    "盗塁死": 0,
    "失策": 2,
    "出塁率": ".348",
    "長打率": ".427",
    "OPS": 0.775
  },
  {
    "月名": "9月",
    "打率": ".321",
    "試合": 22,
    "打席": 98,
    "打数": 84,
    "得点": 14,
    "安打": 27,
    "２Ｂ": 4,
    "３Ｂ": 0,
    "本塁": 3,
    "塁打": 40,
    "打点": 13,
    "三振": 14,
    "四球": 6,
    "敬遠": 0,
    "死球": 3,
    "犠打": 5,
    "犠飛": 0,
    "盗塁": 1,
    "盗塁死": 0,
    "失策": 0,
    "出塁率": ".387",
    "長打率": ".476",
    "OPS": 0.863
  },
  {
    "月名": "10月",
    "打率": "1.000",
    "試合": 1,
    "打席": 3,
    "打数": 3,
    "得点": 2,
    "安打": 3,
    "２Ｂ": 1,
    "３Ｂ": 0,
    "本塁": 0,
    "塁打": 4,
    "打点": 0,
    "三振": 0,
    "四球": 0,
    "敬遠": 0,
    "死球": 0,
    "犠打": 0,
    "犠飛": 0,
    "盗塁": 0,
    "盗塁死": 0,
    "失策": 0,
    "出塁率": "1.000",
    "長打率": "1.333",
    "OPS": 2.333
  },
  {
    "月名": "11月",
    "打率": "-",
    "試合": 0,
    "打席": 0,
    "打数": 0,
    "得点": 0,
    "安打": 0,
    "２Ｂ": 0,
    "３Ｂ": 0,
    "本塁": 0,
    "塁打": 0,
    "打点": 0,
    "三振": 0,
    "四球": 0,
    "敬遠": 0,
    "死球": 0,
    "犠打": 0,
    "犠飛": 0,
    "盗塁": 0,
    "盗塁死": 0,
    "失策": 0,
    "出塁率": "-",
    "長打率": "-",
    "OPS": 0.0
  }
]