[
  {
    "左方向": "42.0% (170)",
    "左方向.1": "42.0% (170)",
    "左方向.2": "42.0% (170)",
    "中方向": "20.0% (81)",
    "中方向.1": "20.0% (81)",
    "中方向.2": "20.0% (81)",
    "右方向": "38.0% (154)",
    "右方向.1": "38.0% (154)",
    "右方向.2": "38.0% (154)"
  },
  {
    "左方向": "安打",
    "左方向.1": "本塁",
    "左方向.2": "凡打",
    "中方向": "安打",
    "中方向.1": "本塁",
    "中方向.2": "凡打",
    "右方向": "安打",
    "右方向.1": "本塁",
    "右方向.2": "凡打"
  },
  {
    "左方向": "40.4% (57)",
    "左方向.1": "100.0% (3)",
    "左方向.2": "42.1% (110)",
    "中方向": "25.5% (36)",
    "中方向.1": "0.0% (0)",
    "中方向.2": "17.2% (45)",
    "右方向": "34.0% (48)",
    "右方向.1": "0.0% (0)",
    "右方向.2": "40.6% (106)"
  }
]