[
  {
    "NOI480.6": "BB/K",
    "GPA.261": "IsoD",
    "RC64.36": "PA/BB",
    "RC275.33": "PA/K",
    "XR63.40": "IsoP",
    "XR275.25": "AB/HR",
    "RCAA19.12": "SecA",
    "XR+17.92": "TA",
    "RCWIN2.25": "PS",
    "XRWIN2.11": "TTO率",
    "BABIP.360": NaN
  },
  {
    "NOI480.6": "0.26",
    "GPA.261": "0.064",
    "RC64.36": "12.86",
    "RC275.33": "3.31",
    "XR63.40": "0.183",
    "XR275.25": "25.35",
    "RCAA19.12": "0.274",
    "XR+17.92": "0.737",
    "RCWIN2.25": "7.73",
    "XRWIN2.11": "41.6%",
    "BABIP.360": NaN
  }
]