[
  {
    "打順": "Home",
    "打率": 0.238,
    "試合": 60,
    "打席": 206,
    "打数": 181,
    "得点": 19,
    "安打": 43,
    "２Ｂ": 10,
    "３Ｂ": 0,
    "本塁": 10,
    "塁打": 83,
    "打点": 26,
    "三振": 32,
    "四球": 22,
    "敬遠": 2,
    "死球": 1,
    "犠打": 0,
    "犠飛": 2,
    "盗塁": 2,
    "盗塁死": 1,
    "失策": 2,
    "出塁率": 0.32,
    "長打率": 0.459,
    "OPS": 0.779
  },
  {
    "打順": "Visitor",
    "打率": 0.223,
    "試合": 48,
    "打席": 171,
    "打数": 157,
    "得点": 6,
    "安打": 35,
    "２Ｂ": 7,
    "３Ｂ": 0,
    "本塁": 2,
    "塁打": 48,
    "打点": 11,
    "三振": 31,
    "四球": 11,
    "敬遠": 2,
    "死球": 1,
    "犠打": 0,
    "犠飛": 2,
    "盗塁": 1,
    "盗塁死": 0,
    "失策": 2,
    "出塁率": 0.275,
    "長打率": 0.306,
    "OPS": 0.581
  }
]