{
  "背番": "8",
  "名前": "渡部聖弥",
  "席": "右",
  "打率": ".259",
  "試合": "109",
  "打席": "452",
  "打数": "425",
  "得点": "42",
  "安打": "110",
  "内安": "8",
  "内安率": "7.3",
  "２Ｂ": "16",
  "３Ｂ": "3",
  "本塁": "12",
  "HR勝敗": "4-7-0",
  "塁打": "168",
  "打点": "43",
  "三振": "85",
  "四球": "21",
  "敬遠": "2",
  "死球": "4",
  "犠打": "0",
  "犠飛": "2",
  "盗塁": "2",
  "盗塁死": "3",
  "成功率": "40.0",
  "失策": "3",
  "捕逸": "0",
  "併殺打": "11",
  "得点圏": ".255",
  "出塁率": ".299",
  "長打率": ".395",
  "OPS": ".694",
  "詳細URL": "https://nf3.sakura.ne.jp/Pacific/L/f/8_stat.htm",
  "nf3_player_id": null
}