[
  {
    "月名": "3・4月",
    "打率": ".253",
    "試合": 24,
    "打席": 99,
    "打数": 87,
    "得点": 8,
    "安打": 22,
    "２Ｂ": 2,
    "３Ｂ": 1,
    "本塁": 0,
    "塁打": 26,
    "打点": 4,
    "三振": 19,
    "四球": 9,
    "敬遠": 0,
    "死球": 1,
    "犠打": 2,
    "犠飛": 0,
    "盗塁": 6,
    "盗塁死": 1,
    "失策": 1,
    "出塁率": ".330",
    "長打率": ".299",
    "OPS": 0.629
  },
  {
    "月名": "5月",
    "打率": ".211",
    "試合": 23,
    "打席": 89,
    "打数": 71,
    "得点": 7,
    "安打": 15,
    "２Ｂ": 0,
    "３Ｂ": 0,
    "本塁": 0,
    "塁打": 15,
    "打点": 3,
    "三振": 14,
    "四球": 15,
    "敬遠": 0,
    "死球": 0,
    "犠打": 3,
    "犠飛": 0,
    "盗塁": 9,
    "盗塁死": 1,
    "失策": 2,
    "出塁率": ".349",
    "長打率": ".211",
    "OPS": 0.56
  },
  {
    "月名": "6月",
    "打率": ".205",
    "試合": 22,
    "打席": 86,
    "打数": 73,
    "得点": 6,
    "安打": 15,
    "２Ｂ": 1,
    "３Ｂ": 0,
    "本塁": 0,
    "塁打": 16,
    "打点": 1,
    "三振": 13,
    "四球": 7,
    "敬遠": 0,
    "死球": 0,
    "犠打": 6,
    "犠飛": 0,
    "盗塁": 6,
    "盗塁死": 3,
    "失策": 0,
    "出塁率": ".275",
    "長打率": ".219",
    "OPS": 0.494
  },
  {
    "月名": "7月",
    "打率": ".265",
    "試合": 19,
    "打席": 40,
    "打数": 34,
    "得点": 5,
    "安打": 9,
    "２Ｂ": 2,
    "３Ｂ": 0,
    "本塁": 1,
    "塁打": 14,
    "打点": 5,
    "三振": 10,
    "四球": 5,
    "敬遠": 0,
    "死球": 0,
    "犠打": 0,
    "犠飛": 1,
    "盗塁": 4,
    "盗塁死": 0,
    "失策": 0,
    "出塁率": ".350",
    "長打率": ".412",
    "OPS": 0.762
  },
  {
    "月名": "8月",
    "打率": ".167",
    "試合": 20,
    "打席": 30,
    "打数": 24,
    "得点": 7,
    "安打": 4,
    "２Ｂ": 0,
    "３Ｂ": 1,
    "本塁": 0,
    "塁打": 6,
    "打点": 1,
    "三振": 6,
    "四球": 4,
    "敬遠": 0,
    "死球": 0,
    "犠打": 2,
    "犠飛": 0,
    "盗塁": 2,
    "盗塁死": 3,
    "失策": 1,
    "出塁率": ".286",
    "長打率": ".250",
    "OPS": 0.536
  },
  {
    "月名": "9月",
    "打率": ".000",
    "試合": 13,
    "打席": 12,
    "打数": 9,
    "得点": 2,
    "安打": 0,
    "２Ｂ": 0,
    "３Ｂ": 0,
    "本塁": 0,
    "塁打": 0,
    "打点": 0,
    "三振": 3,
    "四球": 0,
    "敬遠": 0,
    "死球": 0,
    "犠打": 3,
    "犠飛": 0,
    "盗塁": 1,
    "盗塁死": 0,
    "失策": 0,
    "出塁率": ".000",
    "長打率": ".000",
    "OPS": 0.0
  },
  {
    "月名": "10月",
    "打率": ".000",
    "試合": 3,
    "打席": 1,
    "打数": 1,
    "得点": 1,
    "安打": 0,
    "２Ｂ": 0,
    "３Ｂ": 0,
    "本塁": 0,
    "塁打": 0,
    "打点": 0,
    "三振": 0,
    "四球": 0,
    "敬遠": 0,
    "死球": 0,
    "犠打": 0,
    "犠飛": 0,
    "盗塁": 0,
    "盗塁死": 0,
    "失策": 0,
    "出塁率": ".000",
    "長打率": ".000",
    "OPS": 0.0
  },
  {
    "月名": "11月",
    "打率": "-",
    "試合": 0,
    "打席": 0,
    "打数": 0,
    "得点": 0,
    "安打": 0,
    "２Ｂ": 0,
    "３Ｂ": 0,
    "本塁": 0,
    "塁打": 0,
    "打点": 0,
    "三振": 0,
    "四球": 0,
    "敬遠": 0,
    "死球": 0,
    "犠打": 0,
    "犠飛": 0,
    "盗塁": 0,
    "盗塁死": 0,
    "失策": 0,
    "出塁率": "-",
    "長打率": "-",
    "OPS": 0.0
  }
]