[
  {
    "球種": "ストレート",
    "球数": 272,
    "割合": "40.2%",
    "平均球速 (km/h)": 147.9,
    "空振り": 27,
    "見逃し": 51,
    "ファウル": 52,
    "ボール": 100,
    "ストライク 割合": "47.8%",
    "Whiff%": "22.3%",
    "打率": ".200",
    "打数": 55,
    "安打": 11,
    "ＨＲ": 2,
    "三振": 17,
    "四球": 11,
    "死球": 1
  },
  {
    "球種": "フォーク",
    "球数": 99,
    "割合": "14.6%",
    "平均球速 (km/h)": 136.7,
    "空振り": 16,
    "見逃し": 11,
    "ファウル": 17,
    "ボール": 39,
    "ストライク 割合": "44.4%",
    "Whiff%": "32.7%",
    "打率": ".318",
    "打数": 22,
    "安打": 7,
    "ＨＲ": 0,
    "三振": 6,
    "四球": 2,
    "死球": 0
  },
  {
    "球種": "スライダー",
    "球数": 94,
    "割合": "13.9%",
    "平均球速 (km/h)": 130.3,
    "空振り": 11,
    "見逃し": 21,
    "ファウル": 12,
    "ボール": 35,
    "ストライク 割合": "46.8%",
    "Whiff%": "28.9%",
    "打率": ".222",
    "打数": 18,
    "安打": 4,
    "ＨＲ": 0,
    "三振": 4,
    "四球": 1,
    "死球": 0
  },
  {
    "球種": "カットボール",
    "球数": 53,
    "割合": "7.8%",
    "平均球速 (km/h)": 136.4,
    "空振り": 5,
    "見逃し": 15,
    "ファウル": 6,
    "ボール": 18,
    "ストライク 割合": "49.1%",
    "Whiff%": "25.0%",
    "打率": ".091",
    "打数": 11,
    "安打": 1,
    "ＨＲ": 0,
    "三振": 3,
    "四球": 2,
    "死球": 0
  },
  {
    "球種": "チェンジアップ",
    "球数": 37,
    "割合": "5.5%",
    "平均球速 (km/h)": 129.8,
    "空振り": 10,
    "見逃し": 3,
    "ファウル": 5,
    "ボール": 13,
    "ストライク 割合": "48.6%",
    "Whiff%": "47.6%",
    "打率": ".400",
    "打数": 5,
    "安打": 2,
    "ＨＲ": 0,
    "三振": 0,
    "四球": 0,
    "死球": 0
  },
  {
    "球種": "カーブ",
    "球数": 35,
    "割合": "5.2%",
    "平均球速 (km/h)": 121.5,
    "空振り": 5,
    "見逃し": 8,
    "ファウル": 3,
    "ボール": 17,
    "ストライク 割合": "45.7%",
    "Whiff%": "50.0%",
    "打率": ".250",
    "打数": 4,
    "安打": 1,
    "ＨＲ": 0,
    "三振": 2,
    "四球": 0,
    "死球": 0
  },
  {
    "球種": "ツーシーム",
    "球数": 26,
    "割合": "3.8%",
    "平均球速 (km/h)": 148.1,
    "空振り": 2,
    "見逃し": 5,
    "ファウル": 8,
    "ボール": 7,
    "ストライク 割合": "57.7%",
    "Whiff%": "14.3%",
    "打率": ".333",
    "打数": 6,
    "安打": 2,
    "ＨＲ": 0,
    "三振": 2,
    "四球": 0,
    "死球": 0
  },
  {
    "球種": "シンカー",
    "球数": 20,
    "割合": "3.0%",
    "平均球速 (km/h)": 133.2,
    "空振り": 0,
    "見逃し": 2,
    "ファウル": 3,
    "ボール": 10,
    "ストライク 割合": "25.0%",
    "Whiff%": "0.0%",
    "打率": ".400",
    "打数": 5,
    "安打": 2,
    "ＨＲ": 0,
    "三振": 0,
    "四球": 0,
    "死球": 0
  },
  {
    "球種": "スプリット",
    "球数": 17,
    "割合": "2.5%",
    "平均球速 (km/h)": 142.4,
    "空振り": 4,
    "見逃し": 1,
    "ファウル": 2,
    "ボール": 8,
    "ストライク 割合": "41.2%",
    "Whiff%": "50.0%",
    "打率": ".000",
    "打数": 3,
    "安打": 0,
    "ＨＲ": 0,
    "三振": 1,
    "四球": 1,
    "死球": 0
  },
  {
    "球種": "シュート",
    "球数": 13,
    "割合": "1.9%",
    "平均球速 (km/h)": 144.9,
    "空振り": 0,
    "見逃し": 1,
    "ファウル": 6,
    "ボール": 4,
    "ストライク 割合": "53.8%",
    "Whiff%": "0.0%",
    "打率": ".000",
    "打数": 2,
    "安打": 0,
    "ＨＲ": 0,
    "三振": 0,
    "四球": 0,
    "死球": 0
  },
  {
    "球種": "ナックルカーブ",
    "球数": 6,
    "割合": "0.9%",
    "平均球速 (km/h)": 127.4,
    "空振り": 2,
    "見逃し": 0,
    "ファウル": 1,
    "ボール": 2,
    "ストライク 割合": "50.0%",
    "Whiff%": "50.0%",
    "打率": ".500",
    "打数": 2,
    "安打": 1,
    "ＨＲ": 0,
    "三振": 1,
    "四球": 0,
    "死球": 0
  },
  {
    "球種": "縦スライダー",
    "球数": 4,
    "割合": "0.6%",
    "平均球速 (km/h)": 123.5,
    "空振り": 1,
    "見逃し": 2,
    "ファウル": 1,
    "ボール": 0,
    "ストライク 割合": "100.0%",
    "Whiff%": "50.0%",
    "打率": ".000",
    "打数": 1,
    "安打": 0,
    "ＨＲ": 0,
    "三振": 1,
    "四球": 0,
    "死球": 0
  },
  {
    "球種": "スローカーブ",
    "球数": 1,
    "割合": "0.1%",
    "平均球速 (km/h)": 83.0,
    "空振り": 0,
    "見逃し": 0,
    "ファウル": 0,
    "ボール": 1,
    "ストライク 割合": "0.0%",
    "Whiff%": "-%",
    "打率": "-",
    "打数": 0,
    "安打": 0,
    "ＨＲ": 0,
    "三振": 0,
    "四球": 0,
    "死球": 0
  }
]