[
  {
    "HQS率-": "FIP",
    "SQS率-": "LOB%",
    "被打率.500": "RSAA",
    "被BABIP.571": "RSWIN",
    "被出塁率.500": "PR",
    "被長打率.708": "KD",
    "K/BB4.00": "失点時回数",
    "K/97.20": "援護回",
    "BB/91.80": "援護点",
    "HR/90.00": "救援時回数",
    "GO/AO0.13": "救援時失点",
    "援護率-": "NHB",
    "IPR0.83": "無失点",
    "NHB%0.0%": NaN
  },
  {
    "HQS率-": "1.74",
    "SQS率-": "53.8%",
    "被打率.500": "-4.14",
    "被BABIP.571": "-0.48",
    "被出塁率.500": "-4.31",
    "被長打率.708": "15",
    "K/BB4.00": "2.0",
    "K/97.20": "0",
    "BB/91.80": "0",
    "HR/90.00": "5.0",
    "GO/AO0.13": "6",
    "援護率-": "0",
    "IPR0.83": "2",
    "NHB%0.0%": NaN
  }
]