[
  {
    "球種": "ストレート",
    "球数": 558,
    "割合": "39.3%",
    "平均球速 (km/h)": 147.1,
    "空振り": 14,
    "見逃し": 146,
    "ファウル": 92,
    "ボール": 205,
    "ストライク 割合": "45.2%",
    "Whiff%": "6.8%",
    "打率": ".299",
    "打数": 107,
    "安打": 32,
    "ＨＲ": 3,
    "三振": 7,
    "四球": 16,
    "死球": 0
  },
  {
    "球種": "スライダー",
    "球数": 204,
    "割合": "14.4%",
    "平均球速 (km/h)": 130.5,
    "空振り": 13,
    "見逃し": 51,
    "ファウル": 21,
    "ボール": 74,
    "ストライク 割合": "41.7%",
    "Whiff%": "16.5%",
    "打率": ".314",
    "打数": 51,
    "安打": 16,
    "ＨＲ": 1,
    "三振": 7,
    "四球": 5,
    "死球": 1
  },
  {
    "球種": "カットボール",
    "球数": 161,
    "割合": "11.3%",
    "平均球速 (km/h)": 137.6,
    "空振り": 9,
    "見逃し": 35,
    "ファウル": 33,
    "ボール": 58,
    "ストライク 割合": "47.8%",
    "Whiff%": "13.2%",
    "打率": ".267",
    "打数": 30,
    "安打": 8,
    "ＨＲ": 1,
    "三振": 4,
    "四球": 2,
    "死球": 0
  },
  {
    "球種": "フォーク",
    "球数": 136,
    "割合": "9.6%",
    "平均球速 (km/h)": 135.6,
    "空振り": 16,
    "見逃し": 15,
    "ファウル": 21,
    "ボール": 52,
    "ストライク 割合": "38.2%",
    "Whiff%": "23.2%",
    "打率": ".238",
    "打数": 42,
    "安打": 10,
    "ＨＲ": 0,
    "三振": 10,
    "四球": 2,
    "死球": 0
  },
  {
    "球種": "チェンジアップ",
    "球数": 91,
    "割合": "6.4%",
    "平均球速 (km/h)": 129.1,
    "空振り": 7,
    "見逃し": 12,
    "ファウル": 11,
    "ボール": 39,
    "ストライク 割合": "33.0%",
    "Whiff%": "17.5%",
    "打率": ".269",
    "打数": 26,
    "安打": 7,
    "ＨＲ": 0,
    "三振": 4,
    "四球": 0,
    "死球": 0
  },
  {
    "球種": "ツーシーム",
    "球数": 80,
    "割合": "5.6%",
    "平均球速 (km/h)": 140.3,
    "空振り": 5,
    "見逃し": 25,
    "ファウル": 12,
    "ボール": 25,
    "ストライク 割合": "52.5%",
    "Whiff%": "16.7%",
    "打率": ".200",
    "打数": 15,
    "安打": 3,
    "ＨＲ": 0,
    "三振": 2,
    "四球": 1,
    "死球": 0
  },
  {
    "球種": "シュート",
    "球数": 56,
    "割合": "3.9%",
    "平均球速 (km/h)": 144.6,
    "空振り": 3,
    "見逃し": 15,
    "ファウル": 9,
    "ボール": 16,
    "ストライク 割合": "48.2%",
    "Whiff%": "12.0%",
    "打率": ".333",
    "打数": 15,
    "安打": 5,
    "ＨＲ": 0,
    "三振": 2,
    "四球": 0,
    "死球": 0
  },
  {
    "球種": "カーブ",
    "球数": 53,
    "割合": "3.7%",
    "平均球速 (km/h)": 121.0,
    "空振り": 3,
    "見逃し": 13,
    "ファウル": 4,
    "ボール": 24,
    "ストライク 割合": "37.7%",
    "Whiff%": "18.8%",
    "打率": ".333",
    "打数": 9,
    "安打": 3,
    "ＨＲ": 1,
    "三振": 0,
    "四球": 0,
    "死球": 0
  },
  {
    "球種": "スプリット",
    "球数": 45,
    "割合": "3.2%",
    "平均球速 (km/h)": 138.6,
    "空振り": 7,
    "見逃し": 6,
    "ファウル": 11,
    "ボール": 12,
    "ストライク 割合": "53.3%",
    "Whiff%": "25.9%",
    "打率": ".214",
    "打数": 14,
    "安打": 3,
    "ＨＲ": 0,
    "三振": 5,
    "四球": 1,
    "死球": 0
  },
  {
    "球種": "ナックルカーブ",
    "球数": 14,
    "割合": "1.0%",
    "平均球速 (km/h)": 123.3,
    "空振り": 0,
    "見逃し": 3,
    "ファウル": 2,
    "ボール": 4,
    "ストライク 割合": "35.7%",
    "Whiff%": "0.0%",
    "打率": ".200",
    "打数": 5,
    "安打": 1,
    "ＨＲ": 0,
    "三振": 0,
    "四球": 0,
    "死球": 0
  },
  {
    "球種": "シンカー",
    "球数": 6,
    "割合": "0.4%",
    "平均球速 (km/h)": 133.8,
    "空振り": 0,
    "見逃し": 0,
    "ファウル": 0,
    "ボール": 4,
    "ストライク 割合": "0.0%",
    "Whiff%": "0.0%",
    "打率": ".000",
    "打数": 2,
    "安打": 0,
    "ＨＲ": 0,
    "三振": 0,
    "四球": 0,
    "死球": 0
  },
  {
    "球種": "パワーカーブ",
    "球数": 5,
    "割合": "0.4%",
    "平均球速 (km/h)": 124.8,
    "空振り": 1,
    "見逃し": 1,
    "ファウル": 0,
    "ボール": 2,
    "ストライク 割合": "40.0%",
    "Whiff%": "50.0%",
    "打率": ".000",
    "打数": 2,
    "安打": 0,
    "ＨＲ": 0,
    "三振": 1,
    "四球": 0,
    "死球": 0
  },
  {
    "球種": "パーム",
    "球数": 5,
    "割合": "0.4%",
    "平均球速 (km/h)": 112.4,
    "空振り": 0,
    "見逃し": 0,
    "ファウル": 1,
    "ボール": 1,
    "ストライク 割合": "20.0%",
    "Whiff%": "0.0%",
    "打率": ".333",
    "打数": 3,
    "安打": 1,
    "ＨＲ": 0,
    "三振": 0,
    "四球": 0,
    "死球": 0
  },
  {
    "球種": "スラーブ",
    "球数": 4,
    "割合": "0.3%",
    "平均球速 (km/h)": 120.3,
    "空振り": 0,
    "見逃し": 2,
    "ファウル": 0,
    "ボール": 2,
    "ストライク 割合": "50.0%",
    "Whiff%": "-%",
    "打率": "-",
    "打数": 0,
    "安打": 0,
    "ＨＲ": 0,
    "三振": 0,
    "四球": 0,
    "死球": 0
  },
  {
    "球種": "スローカーブ",
    "球数": 1,
    "割合": "0.1%",
    "平均球速 (km/h)": 90.0,
    "空振り": 0,
    "見逃し": 0,
    "ファウル": 1,
    "ボール": 0,
    "ストライク 割合": "100.0%",
    "Whiff%": "0.0%",
    "打率": "-",
    "打数": 0,
    "安打": 0,
    "ＨＲ": 0,
    "三振": 0,
    "四球": 0,
    "死球": 0
  }
]