[
  {
    "左方向": "55.0% (138)",
    "左方向.1": "55.0% (138)",
    "左方向.2": "55.0% (138)",
    "中方向": "24.7% (62)",
    "中方向.1": "24.7% (62)",
    "中方向.2": "24.7% (62)",
    "右方向": "20.3% (51)",
    "右方向.1": "20.3% (51)",
    "右方向.2": "20.3% (51)"
  },
  {
    "左方向": "安打",
    "左方向.1": "本塁",
    "左方向.2": "凡打",
    "中方向": "安打",
    "中方向.1": "本塁",
    "中方向.2": "凡打",
    "右方向": "安打",
    "右方向.1": "本塁",
    "右方向.2": "凡打"
  },
  {
    "左方向": "60.0% (54)",
    "左方向.1": "58.3% (7)",
    "左方向.2": "51.7% (77)",
    "中方向": "28.9% (26)",
    "中方向.1": "8.3% (1)",
    "中方向.2": "23.5% (35)",
    "右方向": "11.1% (10)",
    "右方向.1": "33.3% (4)",
    "右方向.2": "24.8% (37)"
  }
]