[
  {
    "種別": "Home",
    "防御率": 2.57,
    "試合": 10,
    "先発": 0,
    "救援": 10,
    "勝利": 1,
    "敗戦": 0,
    "HLD": 3,
    "Ｓ": 0,
    "ＨＰ": 4,
    "ＳＰ": 1,
    "救勝": 1,
    "救敗": 0,
    "回数": 7.0,
    "被安": 3,
    "被本": 0,
    "三振": 6,
    "四球": 5,
    "死球": 0,
    "失点": 2,
    "自責": 2,
    "WHIP": 1.14,
    "被打率": 0.143,
    "援護率": "-",
    "IPR": 3.5
  },
  {
    "種別": "Visitor",
    "防御率": 4.05,
    "試合": 9,
    "先発": 0,
    "救援": 9,
    "勝利": 0,
    "敗戦": 0,
    "HLD": 3,
    "Ｓ": 0,
    "ＨＰ": 3,
    "ＳＰ": 0,
    "救勝": 0,
    "救敗": 0,
    "回数": 6.2,
    "被安": 5,
    "被本": 0,
    "三振": 7,
    "四球": 5,
    "死球": 0,
    "失点": 3,
    "自責": 3,
    "WHIP": 1.5,
    "被打率": 0.217,
    "援護率": "-",
    "IPR": 2.22
  }
]