[
  {
    "打率.192": "四球",
    "試合51": "敬遠",
    "打席116": "死球",
    "打数104": "犠打",
    "得点4": "犠飛",
    "安打20": "盗塁",
    "内安0": "盗塁死",
    "内安率0.0": "成功率",
    "２Ｂ4": "失策",
    "３Ｂ0": "捕逸",
    "本塁0": "併殺打",
    "HR勝敗0": "得点圏",
    "塁打24": "出塁率",
    "打点3": "長打率",
    "三振29": "OPS"
  },
  {
    "打率.192": "4",
    "試合51": "0",
    "打席116": "3",
    "打数104": "5",
    "得点4": "0",
    "安打20": "0",
    "内安0": "0",
    "内安率0.0": "-",
    "２Ｂ4": "0",
    "３Ｂ0": "1",
    "本塁0": "3",
    "HR勝敗0": ".200",
    "塁打24": ".243",
    "打点3": ".231",
    "三振29": ".474"
  }
]