[
  {
    "種別": "DayGame",
    "防御率": 0.53,
    "試合": 17,
    "先発": 0,
    "救援": 17,
    "勝利": 1,
    "敗戦": 0,
    "HLD": 15,
    "Ｓ": 0,
    "ＨＰ": 16,
    "ＳＰ": 1,
    "救勝": 1,
    "救敗": 0,
    "回数": 17.0,
    "被安": 8,
    "被本": 0,
    "三振": 16,
    "四球": 4,
    "死球": 0,
    "失点": 1,
    "自責": 1,
    "WHIP": 0.71,
    "被打率": 0.145,
    "援護率": "-",
    "IPR": 17.0
  },
  {
    "種別": "Nighter",
    "防御率": 1.34,
    "試合": 34,
    "先発": 0,
    "救援": 34,
    "勝利": 4,
    "敗戦": 2,
    "HLD": 24,
    "Ｓ": 0,
    "ＨＰ": 28,
    "ＳＰ": 4,
    "救勝": 4,
    "救敗": 2,
    "回数": 33.2,
    "被安": 20,
    "被本": 3,
    "三振": 40,
    "四球": 9,
    "死球": 2,
    "失点": 5,
    "自責": 5,
    "WHIP": 0.86,
    "被打率": 0.174,
    "援護率": "-",
    "IPR": 6.73
  }
]