[
  {
    "NOI206.9": "BB/K",
    "GPA.111": "IsoD",
    "RC-0.44": "PA/BB",
    "RC27-0.28": "PA/K",
    "XR-0.25": "IsoP",
    "XR27-0.16": "AB/HR",
    "RCAA-5.10": "SecA",
    "XR+-4.94": "TA",
    "RCWIN-0.60": "PS",
    "XRWIN-0.58": "TTO率",
    "BABIP.214": NaN
  },
  {
    "NOI206.9": "0.06",
    "GPA.111": "0.019",
    "RC-0.44": "49.00",
    "RC27-0.28": "2.72",
    "XR-0.25": "0.043",
    "XR27-0.16": "-",
    "RCAA-5.10": "0.065",
    "XR+-4.94": "0.220",
    "RCWIN-0.60": "-",
    "XRWIN-0.58": "38.8%",
    "BABIP.214": NaN
  }
]