[
  {
    "打率.211": "四球",
    "試合52": "敬遠",
    "打席171": "死球",
    "打数152": "犠打",
    "得点14": "犠飛",
    "安打32": "盗塁",
    "内安4": "盗塁死",
    "内安率12.5": "成功率",
    "２Ｂ8": "失策",
    "３Ｂ0": "捕逸",
    "本塁2": "併殺打",
    "HR勝敗2-0-0": "得点圏",
    "塁打46": "出塁率",
    "打点8": "長打率",
    "三振34": "OPS"
  },
  {
    "打率.211": "18",
    "試合52": "1",
    "打席171": "1",
    "打数152": "0",
    "得点14": "0",
    "安打32": "0",
    "内安4": "3",
    "内安率12.5": "0.0",
    "２Ｂ8": "3",
    "３Ｂ0": "0",
    "本塁2": "5",
    "HR勝敗2-0-0": ".135",
    "塁打46": ".298",
    "打点8": ".303",
    "三振34": ".601"
  }
]