[
  {
    "チーム": "巨人",
    "防御率": "-",
    "試合": 0,
    "先発": 0,
    "救援": 0,
    "勝利": 0,
    "敗戦": 0,
    "HLD": 0,
    "Ｓ": 0,
    "ＨＰ": 0,
    "ＳＰ": 0,
    "救勝": 0,
    "救敗": 0,
    "回数": 0.0,
    "被安": 0,
    "被本": 0,
    "三振": 0,
    "四球": 0,
    "死球": 0,
    "失点": 0,
    "自責": 0,
    "WHIP": 0.0,
    "被打率": 0.0,
    "援護率": "-",
    "IPR": "-"
  },
  {
    "チーム": "阪神",
    "防御率": "2.00",
    "試合": 3,
    "先発": 3,
    "救援": 0,
    "勝利": 1,
    "敗戦": 1,
    "HLD": 0,
    "Ｓ": 0,
    "ＨＰ": 0,
    "ＳＰ": 0,
    "救勝": 0,
    "救敗": 0,
    "回数": 18.0,
    "被安": 11,
    "被本": 2,
    "三振": 12,
    "四球": 1,
    "死球": 1,
    "失点": 4,
    "自責": 4,
    "WHIP": 0.67,
    "被打率": 0.177,
    "援護率": "2.00",
    "IPR": "-"
  },
  {
    "チーム": "ＤｅＮＡ",
    "防御率": "5.91",
    "試合": 2,
    "先発": 2,
    "救援": 0,
    "勝利": 0,
    "敗戦": 2,
    "HLD": 0,
    "Ｓ": 0,
    "ＨＰ": 0,
    "ＳＰ": 0,
    "救勝": 0,
    "救敗": 0,
    "回数": 10.2,
    "被安": 14,
    "被本": 1,
    "三振": 11,
    "四球": 4,
    "死球": 2,
    "失点": 7,
    "自責": 7,
    "WHIP": 1.69,
    "被打率": 0.318,
    "援護率": "2.70",
    "IPR": "-"
  },
  {
    "チーム": "広島",
    "防御率": "3.00",
    "試合": 1,
    "先発": 1,
    "救援": 0,
    "勝利": 0,
    "敗戦": 1,
    "HLD": 0,
    "Ｓ": 0,
    "ＨＰ": 0,
    "ＳＰ": 0,
    "救勝": 0,
    "救敗": 0,
    "回数": 6.0,
    "被安": 4,
    "被本": 0,
    "三振": 5,
    "四球": 1,
    "死球": 0,
    "失点": 2,
    "自責": 2,
    "WHIP": 0.83,
    "被打率": 0.19,
    "援護率": "1.50",
    "IPR": "-"
  },
  {
    "チーム": "ヤクルト",
    "防御率": "3.68",
    "試合": 3,
    "先発": 3,
    "救援": 0,
    "勝利": 1,
    "敗戦": 1,
    "HLD": 0,
    "Ｓ": 0,
    "ＨＰ": 0,
    "ＳＰ": 0,
    "救勝": 0,
    "救敗": 0,
    "回数": 14.2,
    "被安": 12,
    "被本": 1,
    "三振": 8,
    "四球": 7,
    "死球": 3,
    "失点": 7,
    "自責": 6,
    "WHIP": 1.3,
    "被打率": 0.231,
    "援護率": "2.40",
    "IPR": "-"
  }
]