[
  {
    "条件": "0-0より",
    "打率": ".283",
    "打席": 62,
    "打数": 53,
    "安打": 15,
    "2塁": 5,
    "3塁": 0,
    "本塁": 2,
    "三振": 0,
    "四球": 0,
    "死球": 0,
    "犠打": 7,
    "犠飛": 2,
    "出塁率": 0.273
  },
  {
    "条件": "1-0より",
    "打率": ".222",
    "打席": 29,
    "打数": 27,
    "安打": 6,
    "2塁": 3,
    "3塁": 0,
    "本塁": 0,
    "三振": 0,
    "四球": 1,
    "死球": 0,
    "犠打": 1,
    "犠飛": 0,
    "出塁率": 0.25
  },
  {
    "条件": "2-0より",
    "打率": ".200",
    "打席": 5,
    "打数": 5,
    "安打": 1,
    "2塁": 0,
    "3塁": 0,
    "本塁": 0,
    "三振": 0,
    "四球": 0,
    "死球": 0,
    "犠打": 0,
    "犠飛": 0,
    "出塁率": 0.2
  },
  {
    "条件": "3-0より",
    "打率": "-",
    "打席": 7,
    "打数": 0,
    "安打": 0,
    "2塁": 0,
    "3塁": 0,
    "本塁": 0,
    "三振": 0,
    "四球": 7,
    "死球": 0,
    "犠打": 0,
    "犠飛": 0,
    "出塁率": 1.0
  },
  {
    "条件": "0-1より",
    "打率": ".500",
    "打席": 42,
    "打数": 38,
    "安打": 19,
    "2塁": 3,
    "3塁": 1,
    "本塁": 1,
    "三振": 0,
    "四球": 0,
    "死球": 1,
    "犠打": 2,
    "犠飛": 1,
    "出塁率": 0.5
  },
  {
    "条件": "1-1より",
    "打率": ".514",
    "打席": 37,
    "打数": 35,
    "安打": 18,
    "2塁": 2,
    "3塁": 0,
    "本塁": 2,
    "三振": 0,
    "四球": 0,
    "死球": 1,
    "犠打": 1,
    "犠飛": 0,
    "出塁率": 0.528
  },
  {
    "条件": "2-1より",
    "打率": ".474",
    "打席": 19,
    "打数": 19,
    "安打": 9,
    "2塁": 0,
    "3塁": 1,
    "本塁": 2,
    "三振": 0,
    "四球": 0,
    "死球": 0,
    "犠打": 0,
    "犠飛": 0,
    "出塁率": 0.474
  },
  {
    "条件": "3-1より",
    "打率": ".375",
    "打席": 26,
    "打数": 8,
    "安打": 3,
    "2塁": 1,
    "3塁": 0,
    "本塁": 0,
    "三振": 0,
    "四球": 18,
    "死球": 0,
    "犠打": 0,
    "犠飛": 0,
    "出塁率": 0.808
  },
  {
    "条件": "0-2より",
    "打率": ".255",
    "打席": 56,
    "打数": 55,
    "安打": 14,
    "2塁": 2,
    "3塁": 0,
    "本塁": 2,
    "三振": 23,
    "四球": 0,
    "死球": 0,
    "犠打": 1,
    "犠飛": 0,
    "出塁率": 0.255
  },
  {
    "条件": "1-2より",
    "打率": ".141",
    "打席": 79,
    "打数": 78,
    "安打": 11,
    "2塁": 2,
    "3塁": 0,
    "本塁": 1,
    "三振": 40,
    "四球": 0,
    "死球": 1,
    "犠打": 0,
    "犠飛": 0,
    "出塁率": 0.152
  },
  {
    "条件": "2-2より",
    "打率": ".203",
    "打席": 69,
    "打数": 69,
    "安打": 14,
    "2塁": 0,
    "3塁": 0,
    "本塁": 0,
    "三振": 24,
    "四球": 0,
    "死球": 0,
    "犠打": 0,
    "犠飛": 0,
    "出塁率": 0.203
  },
  {
    "条件": "3-2より",
    "打率": ".255",
    "打席": 77,
    "打数": 51,
    "安打": 13,
    "2塁": 2,
    "3塁": 0,
    "本塁": 1,
    "三振": 17,
    "四球": 26,
    "死球": 0,
    "犠打": 0,
    "犠飛": 0,
    "出塁率": 0.506
  }
]