[
  {
    "防御率4.38": "勝率",
    "試合19": "回数",
    "先発19": "被打者",
    "救援0": "投球数",
    "連投(試)0": "P/IP",
    "連投(日)0": "被安",
    "勝利6": "被本",
    "敗戦6": "三振",
    "HLD0": "四球",
    "Ｓ0": "故意四",
    "ＨＰ0": "死球",
    "ＳＰ0": "暴投",
    "救勝0": "ボーク",
    "救敗0": "失点",
    "完投1": "自責",
    "完封0": "WHIP",
    "無四球0": "QS率"
  },
  {
    "防御率4.38": ".500",
    "試合19": "109.0",
    "先発19": "467",
    "救援0": "1763",
    "連投(試)0": "16.2",
    "連投(日)0": "125",
    "勝利6": "10",
    "敗戦6": "55",
    "HLD0": "22",
    "Ｓ0": "0",
    "ＨＰ0": "4",
    "ＳＰ0": "0",
    "救勝0": "0",
    "救敗0": "54",
    "完投1": "53",
    "完封0": "1.35",
    "無四球0": "31.6%"
  }
]