[
  {
    "打率.300": "四球",
    "試合67": "敬遠",
    "打席276": "死球",
    "打数243": "犠打",
    "得点29": "犠飛",
    "安打73": "盗塁",
    "内安1": "盗塁死",
    "内安率1.4": "成功率",
    "２Ｂ9": "失策",
    "３Ｂ0": "捕逸",
    "本塁13": "併殺打",
    "HR勝敗7-5-0": "得点圏",
    "塁打121": "出塁率",
    "打点39": "長打率",
    "三振59": "OPS"
  },
  {
    "打率.300": "27",
    "試合67": "2",
    "打席276": "6",
    "打数243": "0",
    "得点29": "0",
    "安打73": "0",
    "内安1": "0",
    "内安率1.4": "-",
    "２Ｂ9": "1",
    "３Ｂ0": "0",
    "本塁13": "5",
    "HR勝敗7-5-0": ".391",
    "塁打121": ".384",
    "打点39": ".498",
    "三振59": ".882"
  }
]