[
  {
    "打率.176": "四球",
    "試合18": "敬遠",
    "打席36": "死球",
    "打数34": "犠打",
    "得点0": "犠飛",
    "安打6": "盗塁",
    "内安1": "盗塁死",
    "内安率16.7": "成功率",
    "２Ｂ1": "失策",
    "３Ｂ0": "捕逸",
    "本塁0": "併殺打",
    "HR勝敗0": "得点圏",
    "塁打7": "出塁率",
    "打点0": "長打率",
    "三振7": "OPS"
  },
  {
    "打率.176": "2",
    "試合18": "0",
    "打席36": "0",
    "打数34": "0",
    "得点0": "0",
    "安打6": "0",
    "内安1": "0",
    "内安率16.7": "-",
    "２Ｂ1": "0",
    "３Ｂ0": "1",
    "本塁0": "3",
    "HR勝敗0": ".000",
    "塁打7": ".222",
    "打点0": ".206",
    "三振7": ".428"
  }
]