[
  {
    "打順": "Home",
    "打率": 0.183,
    "試合": 27,
    "打席": 71,
    "打数": 60,
    "得点": 4,
    "安打": 11,
    "２Ｂ": 2,
    "３Ｂ": 0,
    "本塁": 0,
    "塁打": 13,
    "打点": 1,
    "三振": 20,
    "四球": 6,
    "敬遠": 0,
    "死球": 0,
    "犠打": 5,
    "犠飛": 0,
    "盗塁": 0,
    "盗塁死": 1,
    "失策": 0,
    "出塁率": 0.258,
    "長打率": 0.217,
    "OPS": 0.474
  },
  {
    "打順": "Visitor",
    "打率": 0.296,
    "試合": 26,
    "打席": 90,
    "打数": 81,
    "得点": 10,
    "安打": 24,
    "２Ｂ": 2,
    "３Ｂ": 1,
    "本塁": 0,
    "塁打": 28,
    "打点": 9,
    "三振": 14,
    "四球": 4,
    "敬遠": 0,
    "死球": 0,
    "犠打": 5,
    "犠飛": 0,
    "盗塁": 1,
    "盗塁死": 3,
    "失策": 1,
    "出塁率": 0.329,
    "長打率": 0.346,
    "OPS": 0.675
  }
]