[
  {
    "条件": "0-0より",
    "打率": 0.382,
    "打席": 84,
    "打数": 76,
    "安打": 29,
    "2塁": 8,
    "3塁": 1,
    "本塁": 3,
    "三振": 0,
    "四球": 4,
    "死球": 2,
    "犠打": 0,
    "犠飛": 2,
    "出塁率": 0.417
  },
  {
    "条件": "1-0より",
    "打率": 0.333,
    "打席": 31,
    "打数": 30,
    "安打": 10,
    "2塁": 3,
    "3塁": 0,
    "本塁": 2,
    "三振": 0,
    "四球": 1,
    "死球": 0,
    "犠打": 0,
    "犠飛": 0,
    "出塁率": 0.355
  },
  {
    "条件": "2-0より",
    "打率": 0.125,
    "打席": 8,
    "打数": 8,
    "安打": 1,
    "2塁": 0,
    "3塁": 0,
    "本塁": 0,
    "三振": 0,
    "四球": 0,
    "死球": 0,
    "犠打": 0,
    "犠飛": 0,
    "出塁率": 0.125
  },
  {
    "条件": "3-0より",
    "打率": 0.2,
    "打席": 19,
    "打数": 5,
    "安打": 1,
    "2塁": 0,
    "3塁": 0,
    "本塁": 0,
    "三振": 0,
    "四球": 14,
    "死球": 0,
    "犠打": 0,
    "犠飛": 0,
    "出塁率": 0.789
  },
  {
    "条件": "0-1より",
    "打率": 0.368,
    "打席": 38,
    "打数": 38,
    "安打": 14,
    "2塁": 3,
    "3塁": 0,
    "本塁": 2,
    "三振": 0,
    "四球": 0,
    "死球": 0,
    "犠打": 0,
    "犠飛": 0,
    "出塁率": 0.368
  },
  {
    "条件": "1-1より",
    "打率": 0.275,
    "打席": 53,
    "打数": 51,
    "安打": 14,
    "2塁": 2,
    "3塁": 0,
    "本塁": 0,
    "三振": 0,
    "四球": 0,
    "死球": 1,
    "犠打": 0,
    "犠飛": 1,
    "出塁率": 0.283
  },
  {
    "条件": "2-1より",
    "打率": 0.162,
    "打席": 37,
    "打数": 37,
    "安打": 6,
    "2塁": 1,
    "3塁": 0,
    "本塁": 0,
    "三振": 0,
    "四球": 0,
    "死球": 0,
    "犠打": 0,
    "犠飛": 0,
    "出塁率": 0.162
  },
  {
    "条件": "3-1より",
    "打率": 0.333,
    "打席": 28,
    "打数": 9,
    "安打": 3,
    "2塁": 0,
    "3塁": 0,
    "本塁": 1,
    "三振": 0,
    "四球": 19,
    "死球": 0,
    "犠打": 0,
    "犠飛": 0,
    "出塁率": 0.786
  },
  {
    "条件": "0-2より",
    "打率": 0.219,
    "打席": 32,
    "打数": 32,
    "安打": 7,
    "2塁": 1,
    "3塁": 0,
    "本塁": 0,
    "三振": 17,
    "四球": 0,
    "死球": 0,
    "犠打": 0,
    "犠飛": 0,
    "出塁率": 0.219
  },
  {
    "条件": "1-2より",
    "打率": 0.213,
    "打席": 81,
    "打数": 80,
    "安打": 17,
    "2塁": 1,
    "3塁": 0,
    "本塁": 1,
    "三振": 30,
    "四球": 0,
    "死球": 0,
    "犠打": 0,
    "犠飛": 1,
    "出塁率": 0.21
  },
  {
    "条件": "2-2より",
    "打率": 0.232,
    "打席": 102,
    "打数": 99,
    "安打": 23,
    "2塁": 5,
    "3塁": 0,
    "本塁": 1,
    "三振": 33,
    "四球": 0,
    "死球": 3,
    "犠打": 0,
    "犠飛": 0,
    "出塁率": 0.255
  },
  {
    "条件": "3-2より",
    "打率": 0.211,
    "打席": 74,
    "打数": 38,
    "安打": 8,
    "2塁": 1,
    "3塁": 0,
    "本塁": 3,
    "三振": 16,
    "四球": 36,
    "死球": 0,
    "犠打": 0,
    "犠飛": 0,
    "出塁率": 0.595
  }
]