[
  {
    "球種": "ストレート",
    "球数": 347,
    "割合": "49.1%",
    "平均球速 (km/h)": 149.8,
    "空振り": 30,
    "見逃し": 79,
    "ファウル": 81,
    "ボール": 105,
    "ストライク 割合": "54.8%",
    "Whiff%": "18.4%",
    "被打率": 0.147,
    "被打数": 68,
    "被安": 10,
    "被本": 2,
    "奪三振": 18,
    "与四球": 6,
    "与死球": 1
  },
  {
    "球種": "カットボール",
    "球数": 111,
    "割合": "15.7%",
    "平均球速 (km/h)": 141.8,
    "空振り": 20,
    "見逃し": 12,
    "ファウル": 23,
    "ボール": 41,
    "ストライク 割合": "49.5%",
    "Whiff%": "34.5%",
    "被打率": 0.185,
    "被打数": 27,
    "被安": 5,
    "被本": 0,
    "奪三振": 12,
    "与四球": 5,
    "与死球": 0
  },
  {
    "球種": "スライダー",
    "球数": 90,
    "割合": "12.7%",
    "平均球速 (km/h)": 136.4,
    "空振り": 17,
    "見逃し": 14,
    "ファウル": 9,
    "ボール": 27,
    "ストライク 割合": "44.4%",
    "Whiff%": "34.7%",
    "被打率": 0.31,
    "被打数": 29,
    "被安": 9,
    "被本": 0,
    "奪三振": 6,
    "与四球": 0,
    "与死球": 0
  },
  {
    "球種": "チェンジアップ",
    "球数": 89,
    "割合": "12.6%",
    "平均球速 (km/h)": 130.6,
    "空振り": 9,
    "見逃し": 6,
    "ファウル": 14,
    "ボール": 45,
    "ストライク 割合": "32.6%",
    "Whiff%": "23.7%",
    "被打率": 0.278,
    "被打数": 18,
    "被安": 5,
    "被本": 1,
    "奪三振": 3,
    "与四球": 3,
    "与死球": 0
  },
  {
    "球種": "カーブ",
    "球数": 56,
    "割合": "7.9%",
    "平均球速 (km/h)": 114.1,
    "空振り": 1,
    "見逃し": 11,
    "ファウル": 8,
    "ボール": 28,
    "ストライク 割合": "35.7%",
    "Whiff%": "5.9%",
    "被打率": 0.556,
    "被打数": 9,
    "被安": 5,
    "被本": 0,
    "奪三振": 1,
    "与四球": 1,
    "与死球": 0
  },
  {
    "球種": "シンカー",
    "球数": 11,
    "割合": "1.6%",
    "平均球速 (km/h)": 137.6,
    "空振り": 1,
    "見逃し": 1,
    "ファウル": 1,
    "ボール": 5,
    "ストライク 割合": "27.3%",
    "Whiff%": "20.0%",
    "被打率": 0.0,
    "被打数": 4,
    "被安": 0,
    "被本": 0,
    "奪三振": 1,
    "与四球": 0,
    "与死球": 0
  },
  {
    "球種": "フォーク",
    "球数": 3,
    "割合": "0.4%",
    "平均球速 (km/h)": 138.0,
    "空振り": 0,
    "見逃し": 0,
    "ファウル": 0,
    "ボール": 2,
    "ストライク 割合": "0.0%",
    "Whiff%": "0.0%",
    "被打率": 0.0,
    "被打数": 1,
    "被安": 0,
    "被本": 0,
    "奪三振": 0,
    "与四球": 0,
    "与死球": 0
  }
]