{
  "背番": "14",
  "名前": "小島和哉",
  "腕": "左",
  "最終登板": "10/5",
  "防御率": "3.72",
  "試合": "24",
  "先発": "24",
  "救援": "0",
  "連投(試)": "1",
  "連投(日)": "1",
  "勝利": "8",
  "敗戦": "10",
  "HLD": "0",
  "Ｓ": "0",
  "ＨＰ": "0",
  "ＳＰ": "0",
  "救勝": "0",
  "救敗": "0",
  "完投": "0",
  "完封": "0",
  "無四球": "0",
  "勝率": ".444",
  "回数": "145.0",
  "被打者": "619",
  "投球数": "2353",
  "P/IP": "16.2",
  "被安": "144",
  "被本": "20",
  "三振": "92",
  "四球": "54",
  "故意四": "0",
  "死球": "3",
  "暴投": "3",
  "ボーク": "0",
  "失点": "67",
  "自責": "60",
  "詳細URL": "https://nf3.sakura.ne.jp/Pacific/M/p/14_stat.htm",
  "nf3_player_id": "14"
}