[
  {
    "月名": "3・4月",
    "打率": ".160",
    "試合": 14,
    "打席": 54,
    "打数": 50,
    "得点": 3,
    "安打": 8,
    "２Ｂ": 0,
    "３Ｂ": 1,
    "本塁": 0,
    "塁打": 10,
    "打点": 2,
    "三振": 16,
    "四球": 4,
    "敬遠": 0,
    "死球": 0,
    "犠打": 0,
    "犠飛": 0,
    "盗塁": 1,
    "盗塁死": 0,
    "失策": 0,
    "出塁率": ".222",
    "長打率": ".200",
    "OPS": 0.422
  },
  {
    "月名": "5月",
    "打率": ".111",
    "試合": 20,
    "打席": 28,
    "打数": 27,
    "得点": 2,
    "安打": 3,
    "２Ｂ": 2,
    "３Ｂ": 0,
    "本塁": 0,
    "塁打": 5,
    "打点": 3,
    "三振": 10,
    "四球": 1,
    "敬遠": 0,
    "死球": 0,
    "犠打": 0,
    "犠飛": 0,
    "盗塁": 4,
    "盗塁死": 0,
    "失策": 1,
    "出塁率": ".143",
    "長打率": ".185",
    "OPS": 0.328
  },
  {
    "月名": "6月",
    "打率": ".200",
    "試合": 17,
    "打席": 39,
    "打数": 35,
    "得点": 3,
    "安打": 7,
    "２Ｂ": 2,
    "３Ｂ": 0,
    "本塁": 1,
    "塁打": 12,
    "打点": 3,
    "三振": 7,
    "四球": 2,
    "敬遠": 1,
    "死球": 0,
    "犠打": 0,
    "犠飛": 2,
    "盗塁": 1,
    "盗塁死": 0,
    "失策": 2,
    "出塁率": ".231",
    "長打率": ".343",
    "OPS": 0.574
  },
  {
    "月名": "7月",
    "打率": ".241",
    "試合": 15,
    "打席": 35,
    "打数": 29,
    "得点": 4,
    "安打": 7,
    "２Ｂ": 2,
    "３Ｂ": 1,
    "本塁": 0,
    "塁打": 11,
    "打点": 1,
    "三振": 9,
    "四球": 6,
    "敬遠": 0,
    "死球": 0,
    "犠打": 0,
    "犠飛": 0,
    "盗塁": 4,
    "盗塁死": 0,
    "失策": 0,
    "出塁率": ".371",
    "長打率": ".379",
    "OPS": 0.751
  },
  {
    "月名": "8月",
    "打率": ".071",
    "試合": 12,
    "打席": 16,
    "打数": 14,
    "得点": 4,
    "安打": 1,
    "２Ｂ": 1,
    "３Ｂ": 0,
    "本塁": 0,
    "塁打": 2,
    "打点": 1,
    "三振": 5,
    "四球": 1,
    "敬遠": 0,
    "死球": 1,
    "犠打": 0,
    "犠飛": 0,
    "盗塁": 0,
    "盗塁死": 0,
    "失策": 0,
    "出塁率": ".188",
    "長打率": ".143",
    "OPS": 0.33
  },
  {
    "月名": "9月",
    "打率": ".222",
    "試合": 12,
    "打席": 21,
    "打数": 18,
    "得点": 2,
    "安打": 4,
    "２Ｂ": 0,
    "３Ｂ": 0,
    "本塁": 1,
    "塁打": 7,
    "打点": 2,
    "三振": 7,
    "四球": 2,
    "敬遠": 0,
    "死球": 0,
    "犠打": 1,
    "犠飛": 0,
    "盗塁": 1,
    "盗塁死": 0,
    "失策": 0,
    "出塁率": ".300",
    "長打率": ".389",
    "OPS": 0.689
  },
  {
    "月名": "10月",
    "打率": "-",
    "試合": 0,
    "打席": 0,
    "打数": 0,
    "得点": 0,
    "安打": 0,
    "２Ｂ": 0,
    "３Ｂ": 0,
    "本塁": 0,
    "塁打": 0,
    "打点": 0,
    "三振": 0,
    "四球": 0,
    "敬遠": 0,
    "死球": 0,
    "犠打": 0,
    "犠飛": 0,
    "盗塁": 0,
    "盗塁死": 0,
    "失策": 0,
    "出塁率": "-",
    "長打率": "-",
    "OPS": 0.0
  },
  {
    "月名": "11月",
    "打率": "-",
    "試合": 0,
    "打席": 0,
    "打数": 0,
    "得点": 0,
    "安打": 0,
    "２Ｂ": 0,
    "３Ｂ": 0,
    "本塁": 0,
    "塁打": 0,
    "打点": 0,
    "三振": 0,
    "四球": 0,
    "敬遠": 0,
    "死球": 0,
    "犠打": 0,
    "犠飛": 0,
    "盗塁": 0,
    "盗塁死": 0,
    "失策": 0,
    "出塁率": "-",
    "長打率": "-",
    "OPS": 0.0
  }
]