[
  {
    "打順": "Home",
    "打率": 0.259,
    "試合": 61,
    "打席": 226,
    "打数": 189,
    "得点": 21,
    "安打": 49,
    "２Ｂ": 3,
    "３Ｂ": 0,
    "本塁": 0,
    "塁打": 52,
    "打点": 8,
    "三振": 29,
    "四球": 18,
    "敬遠": 0,
    "死球": 2,
    "犠打": 17,
    "犠飛": 0,
    "盗塁": 10,
    "盗塁死": 3,
    "失策": 1,
    "出塁率": 0.33,
    "長打率": 0.275,
    "OPS": 0.605
  },
  {
    "打順": "Visitor",
    "打率": 0.209,
    "試合": 64,
    "打席": 212,
    "打数": 196,
    "得点": 10,
    "安打": 41,
    "２Ｂ": 1,
    "３Ｂ": 0,
    "本塁": 0,
    "塁打": 42,
    "打点": 6,
    "三振": 38,
    "四球": 10,
    "敬遠": 0,
    "死球": 0,
    "犠打": 6,
    "犠飛": 0,
    "盗塁": 11,
    "盗塁死": 4,
    "失策": 4,
    "出塁率": 0.248,
    "長打率": 0.214,
    "OPS": 0.462
  }
]