[
  {
    "チーム": "ソフトバンク",
    "打率": 0.189,
    "試合": 13,
    "打席": 42,
    "打数": 37,
    "得点": 2,
    "安打": 7,
    "２Ｂ": 1,
    "３Ｂ": 0,
    "本塁": 0,
    "塁打": 8,
    "打点": 2,
    "三振": 3,
    "四球": 4,
    "敬遠": 0,
    "死球": 0,
    "犠打": 1,
    "犠飛": 0,
    "盗塁": 1,
    "盗塁死": 1,
    "失策": 0,
    "出塁率": 0.268,
    "長打率": 0.216,
    "OPS": 0.485
  },
  {
    "チーム": "ロッテ",
    "打率": 0.143,
    "試合": 10,
    "打席": 24,
    "打数": 21,
    "得点": 2,
    "安打": 3,
    "２Ｂ": 0,
    "３Ｂ": 0,
    "本塁": 0,
    "塁打": 3,
    "打点": 0,
    "三振": 6,
    "四球": 1,
    "敬遠": 0,
    "死球": 1,
    "犠打": 1,
    "犠飛": 0,
    "盗塁": 0,
    "盗塁死": 0,
    "失策": 1,
    "出塁率": 0.217,
    "長打率": 0.143,
    "OPS": 0.36
  },
  {
    "チーム": "楽天",
    "打率": 0.172,
    "試合": 11,
    "打席": 31,
    "打数": 29,
    "得点": 3,
    "安打": 5,
    "２Ｂ": 0,
    "３Ｂ": 0,
    "本塁": 0,
    "塁打": 5,
    "打点": 0,
    "三振": 4,
    "四球": 2,
    "敬遠": 0,
    "死球": 0,
    "犠打": 0,
    "犠飛": 0,
    "盗塁": 0,
    "盗塁死": 2,
    "失策": 0,
    "出塁率": 0.226,
    "長打率": 0.172,
    "OPS": 0.398
  },
  {
    "チーム": "オリックス",
    "打率": 0.231,
    "試合": 13,
    "打席": 43,
    "打数": 39,
    "得点": 4,
    "安打": 9,
    "２Ｂ": 3,
    "３Ｂ": 1,
    "本塁": 0,
    "塁打": 14,
    "打点": 4,
    "三振": 5,
    "四球": 4,
    "敬遠": 0,
    "死球": 0,
    "犠打": 0,
    "犠飛": 0,
    "盗塁": 0,
    "盗塁死": 0,
    "失策": 0,
    "出塁率": 0.302,
    "長打率": 0.359,
    "OPS": 0.661
  },
  {
    "チーム": "西武",
    "打率": 0.154,
    "試合": 15,
    "打席": 35,
    "打数": 26,
    "得点": 1,
    "安打": 4,
    "２Ｂ": 0,
    "３Ｂ": 0,
    "本塁": 0,
    "塁打": 4,
    "打点": 1,
    "三振": 5,
    "四球": 5,
    "敬遠": 0,
    "死球": 3,
    "犠打": 1,
    "犠飛": 0,
    "盗塁": 1,
    "盗塁死": 1,
    "失策": 1,
    "出塁率": 0.353,
    "長打率": 0.154,
    "OPS": 0.507
  }
]