[
  {
    "防御率4.22": "勝率",
    "試合15": "回数",
    "先発7": "被打者",
    "救援8": "投球数",
    "連投(試)1": "P/IP",
    "連投(日)1": "被安",
    "勝利2": "被本",
    "敗戦3": "三振",
    "HLD1": "四球",
    "Ｓ0": "故意四",
    "ＨＰ1": "死球",
    "ＳＰ0": "暴投",
    "救勝0": "ボーク",
    "救敗0": "失点",
    "完投0": "自責",
    "完封0": "WHIP",
    "無四球0": "QS率"
  },
  {
    "防御率4.22": ".400",
    "試合15": "53.1",
    "先発7": "228",
    "救援8": "844",
    "連投(試)1": "15.8",
    "連投(日)1": "58",
    "勝利2": "6",
    "敗戦3": "45",
    "HLD1": "11",
    "Ｓ0": "1",
    "ＨＰ1": "2",
    "ＳＰ0": "1",
    "救勝0": "0",
    "救敗0": "26",
    "完投0": "25",
    "完封0": "1.29",
    "無四球0": "57.1%"
  }
]