[
  {
    "種別": "Home",
    "防御率": 6.75,
    "試合": 11,
    "先発": 0,
    "救援": 11,
    "勝利": 0,
    "敗戦": 1,
    "HLD": 3,
    "Ｓ": 0,
    "ＨＰ": 3,
    "ＳＰ": 0,
    "救勝": 0,
    "救敗": 1,
    "回数": 9.1,
    "被安": 11,
    "被本": 0,
    "三振": 1,
    "四球": 9,
    "死球": 1,
    "失点": 7,
    "自責": 7,
    "WHIP": 2.14,
    "被打率": 0.297,
    "援護率": "-",
    "IPR": 1.33
  },
  {
    "種別": "Visitor",
    "防御率": 1.0,
    "試合": 9,
    "先発": 0,
    "救援": 9,
    "勝利": 0,
    "敗戦": 0,
    "HLD": 3,
    "Ｓ": 0,
    "ＨＰ": 3,
    "ＳＰ": 0,
    "救勝": 0,
    "救敗": 0,
    "回数": 9.0,
    "被安": 5,
    "被本": 0,
    "三振": 9,
    "四球": 6,
    "死球": 0,
    "失点": 1,
    "自責": 1,
    "WHIP": 1.22,
    "被打率": 0.172,
    "援護率": "-",
    "IPR": 9.0
  }
]