[
  {
    "打率.281": "四球",
    "試合137": "敬遠",
    "打席557": "死球",
    "打数513": "犠打",
    "得点41": "犠飛",
    "安打144": "盗塁",
    "内安17": "盗塁死",
    "内安率11.8": "成功率",
    "２Ｂ14": "失策",
    "３Ｂ0": "捕逸",
    "本塁3": "併殺打",
    "HR勝敗1-2-0": "得点圏",
    "塁打167": "出塁率",
    "打点51": "長打率",
    "三振102": "OPS"
  },
  {
    "打率.281": "28",
    "試合137": "2",
    "打席557": "3",
    "打数513": "10",
    "得点41": "3",
    "安打144": "6",
    "内安17": "2",
    "内安率11.8": "75.0",
    "２Ｂ14": "10",
    "３Ｂ0": "0",
    "本塁3": "14",
    "HR勝敗1-2-0": ".355",
    "塁打167": ".320",
    "打点51": ".326",
    "三振102": ".645"
  }
]