[
  {
    "打率.235": "四球",
    "試合26": "敬遠",
    "打席18": "死球",
    "打数17": "犠打",
    "得点2": "犠飛",
    "安打4": "盗塁",
    "内安0": "盗塁死",
    "内安率0.0": "成功率",
    "２Ｂ3": "失策",
    "３Ｂ0": "捕逸",
    "本塁0": "併殺打",
    "HR勝敗0": "得点圏",
    "塁打7": "出塁率",
    "打点2": "長打率",
    "三振5": "OPS"
  },
  {
    "打率.235": "1",
    "試合26": "0",
    "打席18": "0",
    "打数17": "0",
    "得点2": "0",
    "安打4": "1",
    "内安0": "0",
    "内安率0.0": "100.0",
    "２Ｂ3": "1",
    "３Ｂ0": "0",
    "本塁0": "0",
    "HR勝敗0": ".000",
    "塁打7": ".278",
    "打点2": ".412",
    "三振5": ".690"
  }
]