[
  {
    "種別": "Home",
    "防御率": 4.05,
    "試合": 5,
    "先発": 0,
    "救援": 5,
    "勝利": 0,
    "敗戦": 0,
    "HLD": 0,
    "Ｓ": 0,
    "ＨＰ": 0,
    "ＳＰ": 0,
    "救勝": 0,
    "救敗": 0,
    "回数": 6.2,
    "被安": 8,
    "被本": 1,
    "三振": 6,
    "四球": 3,
    "死球": 2,
    "失点": 4,
    "自責": 3,
    "WHIP": 1.65,
    "被打率": 0.276,
    "援護率": "-",
    "IPR": 1.67
  },
  {
    "種別": "Visitor",
    "防御率": 7.94,
    "試合": 5,
    "先発": 0,
    "救援": 5,
    "勝利": 0,
    "敗戦": 0,
    "HLD": 0,
    "Ｓ": 0,
    "ＨＰ": 0,
    "ＳＰ": 0,
    "救勝": 0,
    "救敗": 0,
    "回数": 5.2,
    "被安": 6,
    "被本": 1,
    "三振": 6,
    "四球": 3,
    "死球": 0,
    "失点": 5,
    "自責": 5,
    "WHIP": 1.59,
    "被打率": 0.273,
    "援護率": "-",
    "IPR": 1.13
  }
]