[
  {
    "NOI434.6": "BB/K",
    "GPA.227": "IsoD",
    "RC18.54": "PA/BB",
    "RC273.63": "PA/K",
    "XR18.91": "IsoP",
    "XR273.70": "AB/HR",
    "RCAA-0.95": "SecA",
    "XR+-0.81": "TA",
    "RCWIN-0.11": "PS",
    "XRWIN-0.09": "TTO率",
    "BABIP.275": NaN
  },
  {
    "NOI434.6": "0.45",
    "GPA.227": "0.092",
    "RC18.54": "15.23",
    "RC273.63": "6.83",
    "XR18.91": "0.076",
    "XR273.70": "86.00",
    "RCAA-0.95": "0.157",
    "XR+-0.81": "0.581",
    "RCWIN-0.11": "1.33",
    "XRWIN-0.09": "22.2%",
    "BABIP.275": NaN
  }
]