{
  "背番": "8",
  "名前": "辰己涼介",
  "席": "左",
  "打率": ".240",
  "試合": "114",
  "打席": "422",
  "打数": "367",
  "得点": "36",
  "安打": "88",
  "内安": "8",
  "内安率": "9.1",
  "２Ｂ": "12",
  "３Ｂ": "2",
  "本塁": "7",
  "HR勝敗": "5-2-0",
  "塁打": "125",
  "打点": "32",
  "三振": "91",
  "四球": "40",
  "敬遠": "0",
  "死球": "9",
  "犠打": "1",
  "犠飛": "5",
  "盗塁": "20",
  "盗塁死": "0",
  "成功率": "100.0",
  "失策": "1",
  "捕逸": "0",
  "併殺打": "12",
  "得点圏": ".179",
  "出塁率": ".325",
  "長打率": ".341",
  "OPS": ".666",
  "詳細URL": "https://nf3.sakura.ne.jp/Pacific/E/f/8_stat.htm",
  "nf3_player_id": null
}