{
  "背番": "53",
  "名前": "颯",
  "席": "左",
  "打率": "1.000",
  "試合": "27",
  "打席": "1",
  "打数": "1",
  "得点": "0",
  "安打": "1",
  "内安": "0",
  "内安率": "0.0",
  "２Ｂ": "0",
  "３Ｂ": "0",
  "本塁": "0",
  "HR勝敗": "-",
  "塁打": "1",
  "打点": "0",
  "三振": "0",
  "四球": "0",
  "敬遠": "0",
  "死球": "0",
  "犠打": "0",
  "犠飛": "0",
  "盗塁": "0",
  "盗塁死": "0",
  "成功率": "-",
  "失策": "0",
  "捕逸": "0",
  "併殺打": "0",
  "得点圏": "-",
  "出塁率": "1.000",
  "長打率": "1.000",
  "OPS": "2.000",
  "詳細URL": "https://nf3.sakura.ne.jp/Central/DB/f/53_stat.htm",
  "nf3_player_id": null
}