[
  {
    "種別": "Home",
    "防御率": 1.99,
    "試合": 4,
    "先発": 4,
    "救援": 0,
    "勝利": 2,
    "敗戦": 1,
    "HLD": 0,
    "Ｓ": 0,
    "ＨＰ": 0,
    "ＳＰ": 0,
    "救勝": 0,
    "救敗": 0,
    "回数": 22.2,
    "被安": 13,
    "被本": 0,
    "三振": 24,
    "四球": 17,
    "死球": 1,
    "失点": 5,
    "自責": 5,
    "WHIP": 1.32,
    "被打率": 0.171,
    "援護率": 5.32,
    "IPR": "-"
  },
  {
    "種別": "Visitor",
    "防御率": 0.69,
    "試合": 2,
    "先発": 2,
    "救援": 0,
    "勝利": 1,
    "敗戦": 0,
    "HLD": 0,
    "Ｓ": 0,
    "ＨＰ": 0,
    "ＳＰ": 0,
    "救勝": 0,
    "救敗": 0,
    "回数": 13.0,
    "被安": 5,
    "被本": 0,
    "三振": 10,
    "四球": 6,
    "死球": 0,
    "失点": 1,
    "自責": 1,
    "WHIP": 0.85,
    "被打率": 0.119,
    "援護率": 1.8,
    "IPR": "-"
  }
]