[
  {
    "HQS率21.4%": "FIP",
    "SQS率21.4%": "LOB%",
    "被打率.315": "RSAA",
    "被BABIP.346": "RSWIN",
    "被出塁率.374": "PR",
    "被長打率.398": "KD",
    "K/BB1.30": "失点時回数",
    "K/94.20": "援護回",
    "BB/93.22": "援護点",
    "HR/90.14": "救援時回数",
    "GO/AO1.28": "救援時失点",
    "援護率2.87": "NHB",
    "IPR-": "無失点",
    "NHB%-": NaN
  },
  {
    "HQS率21.4%": "3.26",
    "SQS率21.4%": "65.3%",
    "被打率.315": "-14.09",
    "被BABIP.346": "-1.63",
    "被出塁率.374": "-10.27",
    "被長打率.398": "213",
    "K/BB1.30": "0.0",
    "K/94.20": "69",
    "BB/93.22": "22",
    "HR/90.14": "0.0",
    "GO/AO1.28": "0",
    "援護率2.87": "0",
    "IPR-": "0",
    "NHB%-": NaN
  }
]